katcpcli/CommandDispatcher.py
katcpcli/StreamClient.py
katcpcli/UI.py
katcpcli/__init__.py
katcpcli/app.py
katcpcli/config.py
katcpcli/main.py
katcpcli-0.9.0.dist-info/LICENSE
katcpcli-0.9.0.dist-info/METADATA
katcpcli-0.9.0.dist-info/WHEEL
katcpcli-0.9.0.dist-info/entry_points.txt
katcpcli-0.9.0.dist-info/top_level.txt
katcpcli-0.9.0.dist-info/RECORD
