Metadata-Version: 2.1
Name: katcpcli
Version: 0.9.0
Summary: A command-line client for katcp devices.
Author-email: Tobias Winchen <twinchen@mpifr.de>
License: Copyright 2022 Max Planck Institute for Radio Astronomy (MPIfR)
Project-URL: Homepage, https://gitlab.mpcdf.mpg.de/twinchen/katcpcli
Classifier: Programming Language :: Python :: 3
Classifier: License :: OSI Approved :: BSD License
Classifier: Operating System :: OS Independent
Requires-Python: >=3.8
License-File: LICENSE
Requires-Dist: aiokatcp
Requires-Dist: prompt-toolkit
